README.md
setup.py
zgtools/__init__.py
zgtools/backtest_handle.py
zgtools/data_tool.py
zgtools/db_handle.py
zgtools.egg-info/PKG-INFO
zgtools.egg-info/SOURCES.txt
zgtools.egg-info/dependency_links.txt
zgtools.egg-info/top_level.txt