Metadata-Version: 1.1
Name: zgtools
Version: 0.1.8
Summary: quant tools
Home-page: https://gitee.com/l_stone/zg_tools
Author: stone
Author-email: 393928715@qq.com
License: MIT
Platform: UNKNOWN
Classifier: Programming Language :: Python :: 3
Classifier: License :: OSI Approved :: MIT License
Classifier: Operating System :: OS Independent
